psiresp/__init__.py
psiresp/_version.py
psiresp/configs.py
psiresp/conformer.py
psiresp/due.py
psiresp/multiresp.py
psiresp/orientation.py
psiresp/resp.py
psiresp/resp2.py
psiresp/utils.py
psiresp/vdwradii.py
psiresp-0.0a0.dist-info/LICENSE
psiresp-0.0a0.dist-info/WHEEL
psiresp-0.0a0.dist-info/METADATA
psiresp-0.0a0.dist-info/RECORD
