Metadata-Version: 2.1
Name: psiresp
Version: 0.0a0
Summary: psiresp
Home-page: https://github.com/lilyminium/psiresp
License: UNKNOWN
Author: Lily Wang
Author-email: lily.wang@anu.edu.au
Requires-Python: >=3.6
Classifier: License :: OSI Approved :: GNU Lesser General Public License v3 or later (LGPLv3+)
Classifier: Programming Language :: Python :: 3
Requires-Dist: numpy
Requires-Dist: qcelemental
Requires-Dist: duecredit
Requires-Dist: sphinx ; extra == "doc"
Requires-Dist: sphinx_rtd_theme ; extra == "doc"
Requires-Dist: sphinxcontrib-bibtex ; extra == "doc"
Requires-Dist: sphinx-sitemap ; extra == "doc"
Requires-Dist: pytest ; extra == "test"
Requires-Dist: pytest-cov ; extra == "test"
Provides-Extra: doc
Provides-Extra: test
